nd2_dask/__init__.py
nd2_dask/nd2_reader.py
nd2_dask/_tests/__init__.py
nd2_dask/_tests/test_nd2_reader.py
nd2_dask-0.0.7.dist-info/LICENSE
nd2_dask-0.0.7.dist-info/METADATA
nd2_dask-0.0.7.dist-info/WHEEL
nd2_dask-0.0.7.dist-info/entry_points.txt
nd2_dask-0.0.7.dist-info/top_level.txt
nd2_dask-0.0.7.dist-info/RECORD
