Metadata-Version: 2.1
Name: nd2-dask
Version: 0.0.7
Summary: Plugin to load nd2 data into napari
Home-page: https://github.com/DragaDoncila/nd2-dask
Author: Draga Doncila Pop
Author-email: ddon0001@student.monash.edu
License: BSD-3
Classifier: Development Status :: 4 - Beta
Classifier: Intended Audience :: Developers
Classifier: Topic :: Software Development :: Testing
Classifier: Programming Language :: Python
Classifier: Programming Language :: Python :: 3
Classifier: Programming Language :: Python :: 3.6
Classifier: Programming Language :: Python :: 3.7
Classifier: Programming Language :: Python :: 3.8
Classifier: Programming Language :: Python :: Implementation :: CPython
Classifier: Programming Language :: Python :: Implementation :: PyPy
Classifier: Operating System :: OS Independent
Classifier: License :: OSI Approved :: BSD License
Requires-Python: >=3.6
License-File: LICENSE
Requires-Dist: napari-plugin-engine (>=0.1.4)
Requires-Dist: numpy
Requires-Dist: nd2reader
Requires-Dist: dask
Requires-Dist: toolz
Requires-Dist: vispy
